README.rst
setup.py
CLIP_Crawler.egg-info/PKG-INFO
CLIP_Crawler.egg-info/SOURCES.txt
CLIP_Crawler.egg-info/dependency_links.txt
CLIP_Crawler.egg-info/requires.txt
CLIP_Crawler.egg-info/top_level.txt
CLIPy/__init__.py
CLIPy/crawler.py
CLIPy/interface.py
CLIPy/items.py
CLIPy/parser.py
CLIPy/pipelines.py
CLIPy/processors.py
CLIPy/session.py
CLIPy/settings.py
CLIPy/urls.py
CLIPy/database/__init__.py
CLIPy/database/candidates.py
CLIPy/database/database.py
CLIPy/database/models.py
CLIPy/database/types.py
CLIPy/utils/__init__.py
CLIPy/utils/populate.py
CLIPy/utils/utils.py
tests/__init__.py
tests/parsers.py
tests/tools/__init__.py
tests/tools/minimize.py