Metadata-Version: 1.1
Name: CLIP-Crawler
Version: 0.7.0
Summary: A wrapper/crawler meant to fetch information from the Campus Life Integration Platform (clip.fct.unl.pt)
Home-page: https://gitlab.com/claudiop/CLIPy
Author: Cláudio Pereira
Author-email: development@claudiop.com
License: GPL V3
Keywords: CLIP Clip FCT UNL wrapper crawler
Platform: UNKNOWN
Classifier: Development Status :: 3 - Alpha
Classifier: Topic :: Utilities
Classifier: License :: OSI Approved :: GNU General Public License v3 (GPLv3)
Classifier: Natural Language :: Portuguese
Classifier: Topic :: Internet :: WWW/HTTP
Classifier: Topic :: Internet :: WWW/HTTP :: Dynamic Content
Classifier: Topic :: Text Processing :: Markup :: HTML
